chatstack/__init__.py
chatstack/chatstack.py
chatstack/pricing.py
chatstack/retry.py
chatstack-0.1.5.dist-info/LICENSE
chatstack-0.1.5.dist-info/METADATA
chatstack-0.1.5.dist-info/WHEEL
chatstack-0.1.5.dist-info/top_level.txt
chatstack-0.1.5.dist-info/RECORD
