Metadata-Version: 2.1
Name: chatstack
Version: 0.1.5
Summary: Message-based LLM tools.
Author-email: Bill Kish <bk@jiggy.ai>
Project-URL: Homepage, https://github.com/jiggy-ai/chatstack
Project-URL: Bug Tracker, https://github.com/jiggy-ai/chatstack/issues
Classifier: Programming Language :: Python :: 3
Classifier: License :: OSI Approved :: Apache Software License
Classifier: Operating System :: OS Independent
Requires-Python: >=3.7
License-File: LICENSE
Requires-Dist: pydantic
Requires-Dist: openai
Requires-Dist: tiktoken
Requires-Dist: loguru
